__main__.py
f_m3u8.py
f_spoti.py
f_ytmusic.py
musync-0.0.1.dist-info/LICENSE
musync-0.0.1.dist-info/METADATA
musync-0.0.1.dist-info/WHEEL
musync-0.0.1.dist-info/entry_points.txt
musync-0.0.1.dist-info/top_level.txt
musync-0.0.1.dist-info/RECORD
