Metadata-Version: 2.1
Name: musync
Version: 0.0.1
Summary: Gets your music from Spotify and downloads it from Youtube Music
Author-email: Vittorio Lo Mele <vittorio@mrbackslash.it>
License: 
Project-URL: Homepage, https://github.com/vittodevit/musync
Keywords: music,python,spotify,downloader
Classifier: License :: OSI Approved :: Apache Software License
Classifier: Programming Language :: Python :: 3.8
Requires-Python: >=3.8
License-File: LICENSE
Requires-Dist: spotipy
Requires-Dist: ffmpeg
Requires-Dist: click
Requires-Dist: mutagen
Requires-Dist: ytmusicapi
Requires-Dist: yt-dlp
